{
  "form_name": "롯데카드_부채증명서, 카드거래내역서",
  "bank_name": "롯데카드",
  "doc_type": "부채증명서, 카드거래내역서",
  "total_pages": 2,
  "pages": [
    {
      "page": 1,
      "fields": [
        {
          "field_id": "client_name",
          "x_pct": 29.9,
          "y_pct": 35.4,
          "font_size": 11,
          "type": "text",
          "spacing": 0.0
        },
        {
          "field_id": "client_address",
          "x_pct": 29.9,
          "y_pct": 38.8,
          "font_size": 11,
          "type": "text",
          "spacing": 0.0
        },
        {
          "field_id": "agent_name",
          "x_pct": 62.0,
          "y_pct": 43.5,
          "font_size": 11,
          "type": "text",
          "spacing": 0.0
        },
        {
          "field_id": "date_month",
          "x_pct": 69.0,
          "y_pct": 59.5,
          "font_size": 11,
          "type": "text",
          "spacing": 0.0
        },
        {
          "field_id": "date_day",
          "x_pct": 78.0,
          "y_pct": 59.5,
          "font_size": 11,
          "type": "text",
          "spacing": 0.0
        },
        {
          "field_id": "date7_year_suffix",
          "x_pct": 59.3,
          "y_pct": 62.7,
          "font_size": 11,
          "type": "text",
          "spacing": 0.0
        },
        {
          "field_id": "date7_month",
          "x_pct": 69.0,
          "y_pct": 62.7,
          "font_size": 11,
          "type": "text",
          "spacing": 0.0
        },
        {
          "field_id": "date7_day",
          "x_pct": 78.0,
          "y_pct": 62.7,
          "font_size": 11,
          "type": "text",
          "spacing": 0.0
        },
        {
          "field_id": "date_year_suffix",
          "x_pct": 59.3,
          "y_pct": 59.5,
          "font_size": 11,
          "type": "text",
          "spacing": 0.0
        },
        {
          "field_id": "agent_sign",
          "x_pct": 70.5,
          "y_pct": 44.0,
          "font_size": 11,
          "type": "image",
          "width_pct": 7.0,
          "height_pct": 2.2
        },
        {
          "field_id": "client_id_full",
          "x_pct": 70.2,
          "y_pct": 49.2,
          "font_size": 11,
          "type": "text",
          "spacing": 0.0
        }
      ]
    },
    {
      "page": 2,
      "fields": [
        {
          "field_id": "client_name",
          "x_pct": 25.1,
          "y_pct": 58.8,
          "font_size": 11,
          "type": "text",
          "spacing": 0.0
        },
        {
          "field_id": "client_phone",
          "x_pct": 25.1,
          "y_pct": 62.0,
          "font_size": 11,
          "type": "text",
          "spacing": 0.0
        },
        {
          "field_id": "client_address",
          "x_pct": 25.1,
          "y_pct": 65.0,
          "font_size": 11,
          "type": "text",
          "spacing": 0.0
        },
        {
          "field_id": "agent_name",
          "x_pct": 62.0,
          "y_pct": 58.8,
          "font_size": 11,
          "type": "text",
          "spacing": 0.0
        },
        {
          "field_id": "agent_phone",
          "x_pct": 62.0,
          "y_pct": 62.0,
          "font_size": 11,
          "type": "text",
          "spacing": 0.0
        },
        {
          "field_id": "date_year_suffix",
          "x_pct": 47.4,
          "y_pct": 51.4,
          "font_size": 11,
          "type": "text",
          "spacing": 0.0
        },
        {
          "field_id": "date_month",
          "x_pct": 59.1,
          "y_pct": 51.4,
          "font_size": 11,
          "type": "text",
          "spacing": 0.0
        },
        {
          "field_id": "date_day",
          "x_pct": 73.6,
          "y_pct": 51.4,
          "font_size": 11,
          "type": "text",
          "spacing": 0.0
        }
      ]
    }
  ]
}