{
  "form_name": "이진우_재직증명서",
  "bank_name": "이진우",
  "doc_type": "재직증명서",
  "total_pages": 1,
  "pages": [
    {
      "page": 1,
      "fields": [
        {
          "field_id": "date_year_suffix",
          "x_pct": 35.0,
          "y_pct": 69.7,
          "font_size": 11,
          "type": "text",
          "spacing": 0.0
        },
        {
          "field_id": "date_month",
          "x_pct": 42.0,
          "y_pct": 69.7,
          "font_size": 11,
          "type": "text",
          "spacing": 0.0
        },
        {
          "field_id": "date_day",
          "x_pct": 49.0,
          "y_pct": 69.7,
          "font_size": 11,
          "type": "text",
          "spacing": 0.0
        }
      ]
    }
  ]
}